apispec_webframeworks/__init__.py
apispec_webframeworks/bottle.py
apispec_webframeworks/flask.py
apispec_webframeworks/tornado.py
apispec_webframeworks/tests/__init__.py
apispec_webframeworks/tests/test_ext_bottle.py
apispec_webframeworks/tests/test_ext_flask.py
apispec_webframeworks/tests/test_ext_tornado.py
apispec_webframeworks/tests/utils.py
apispec_webframeworks-0.5.1.dist-info/AUTHORS.rst
apispec_webframeworks-0.5.1.dist-info/LICENSE
apispec_webframeworks-0.5.1.dist-info/METADATA
apispec_webframeworks-0.5.1.dist-info/WHEEL
apispec_webframeworks-0.5.1.dist-info/top_level.txt
apispec_webframeworks-0.5.1.dist-info/RECORD
