Metadata-Version: 2.1
Name: apispec-webframeworks
Version: 0.5.1
Summary: Web framework plugins for apispec.
Home-page: https://github.com/marshmallow-code/apispec-webframeworks
Author: Steven Loria
Author-email: sloria1@gmail.com
License: MIT
Project-URL: Funding, https://opencollective.com/marshmallow
Project-URL: Issues, https://github.com/marshmallow-code/apispec-webframeworks/issues
Keywords: apispec,swagger,openapi,specification,documentation,spec,rest,api,web,flask,tornado,bottle,frameworks
Platform: UNKNOWN
Classifier: Development Status :: 4 - Beta
Classifier: Intended Audience :: Developers
Classifier: License :: OSI Approved :: MIT License
Classifier: Natural Language :: English
Classifier: Programming Language :: Python :: 3
Classifier: Programming Language :: Python :: 3.6
Classifier: Programming Language :: Python :: 3.7
Requires-Python: >=3.6
Requires-Dist: apispec[yaml] (>=2.0.0)
Provides-Extra: dev
Requires-Dist: pytest ; extra == 'dev'
Requires-Dist: mock ; extra == 'dev'
Requires-Dist: Flask (==1.1.1) ; extra == 'dev'
Requires-Dist: tornado ; extra == 'dev'
Requires-Dist: bottle (==0.12.17) ; extra == 'dev'
Requires-Dist: flake8 (==3.7.9) ; extra == 'dev'
Requires-Dist: flake8-bugbear (==19.8.0) ; extra == 'dev'
Requires-Dist: pre-commit (~=1.18) ; extra == 'dev'
Requires-Dist: tox ; extra == 'dev'
Provides-Extra: lint
Requires-Dist: flake8 (==3.7.9) ; extra == 'lint'
Requires-Dist: flake8-bugbear (==19.8.0) ; extra == 'lint'
Requires-Dist: pre-commit (~=1.18) ; extra == 'lint'
Provides-Extra: tests
Requires-Dist: pytest ; extra == 'tests'
Requires-Dist: mock ; extra == 'tests'
Requires-Dist: Flask (==1.1.1) ; extra == 'tests'
Requires-Dist: tornado ; extra == 'tests'
Requires-Dist: bottle (==0.12.17) ; extra == 'tests'
